agentdna/__init__.py
agentdna/handler.py
agentdna/node_client.py
agentdna/token.txt
agentdna/trust.py
agentdna-0.1.2.dist-info/METADATA
agentdna-0.1.2.dist-info/WHEEL
agentdna-0.1.2.dist-info/top_level.txt
agentdna-0.1.2.dist-info/RECORD
