Metadata-Version: 2.4
Name: agentdna
Version: 0.1.2
Summary: Rubix agent DNA: trust + node client + handler utilities
Author-email: Aparna Ullas <aparnaullas97@gmail.com>
License: MIT
Requires-Python: >=3.11
Requires-Dist: requests>=2.0.0
Requires-Dist: python-dotenv>=1.0.0
Requires-Dist: rubix-py
